{
  "page": {
    "id": "hz9lv5sckdkc",
    "name": "Glitch",
    "url": "https://status.glitch.com",
    "time_zone": "America/New_York",
    "updated_at": "2023-03-15T00:43:01.879-04:00"
  },
  "components": [
    {
      "id": "7fygdzlzf9v7",
      "name": "Editor",
      "status": "major_outage",
      "created_at": "2016-12-12T17:24:32.054-05:00",
      "updated_at": "2023-03-15T00:40:53.765-04:00",
      "position": 1,
      "description": "glitch.com/edit/",
      "showcase": false,
      "start_date": null,
      "group_id": null,
      "page_id": "hz9lv5sckdkc",
      "group": false,
      "only_show_if_degraded": false
    },
    {
      "id": "vj4m8h9z3m0b",
      "name": "Community Site",
      "status": "partial_outage",
      "created_at": "2016-12-12T17:25:22.182-05:00",
      "updated_at": "2023-03-15T00:40:53.779-04:00",
      "position": 2,
      "description": "glitch.com",
      "showcase": false,
      "start_date": null,
      "group_id": null,
      "page_id": "hz9lv5sckdkc",
      "group": false,
      "only_show_if_degraded": false
    },
    {
      "id": "qmp1k3jcxdzx",
      "name": "API",
      "status": "major_outage",
      "created_at": "2016-12-12T17:24:38.276-05:00",
      "updated_at": "2023-03-15T00:40:53.792-04:00",
      "position": 3,
      "description": "api.glitch.com",
      "showcase": false,
      "start_date": null,
      "group_id": null,
      "page_id": "hz9lv5sckdkc",
      "group": false,
      "only_show_if_degraded": false
    },
    {
      "id": "mz7hvb42r41c",
      "name": "Project Hosting",
      "status": "operational",
      "created_at": "2016-12-12T17:24:50.880-05:00",
      "updated_at": "2023-03-06T17:44:54.751-05:00",
      "position": 4,
      "description": "your-app.glitch.me",
      "showcase": false,
      "start_date": null,
      "group_id": null,
      "page_id": "hz9lv5sckdkc",
      "group": false,
      "only_show_if_degraded": false
    },
    {
      "id": "zvlc3gkzqxb0",
      "name": "Support Forum",
      "status": "operational",
      "created_at": "2019-11-19T12:50:03.928-05:00",
      "updated_at": "2020-04-12T20:37:47.782-04:00",
      "position": 5,
      "description": "Discourse-powered forum at support.glitch.com",
      "showcase": false,
      "start_date": null,
      "group_id": null,
      "page_id": "hz9lv5sckdkc",
      "group": false,
      "only_show_if_degraded": false
    }
  ],
  "incidents": [
    {
      "id": "qkm46x4j4h6f",
      "name": "API outage causing login and editing errors",
      "status": "investigating",
      "created_at": "2023-03-15T00:40:53.727-04:00",
      "updated_at": "2023-03-15T00:40:53.834-04:00",
      "monitoring_at": null,
      "resolved_at": null,
      "impact": "major",
      "shortlink": "https://stspg.io/s3wlz9gms6pv",
      "started_at": "2023-03-15T00:40:53.720-04:00",
      "page_id": "hz9lv5sckdkc",
      "incident_updates": [
        {
          "id": "05rh5s5n3k91",
          "status": "investigating",
          "body": "An API failure is causing users to be unable to log in or access the editor. We are working to identify the cause.",
          "incident_id": "qkm46x4j4h6f",
          "created_at": "2023-03-15T00:40:53.831-04:00",
          "updated_at": "2023-03-15T00:40:53.831-04:00",
          "display_at": "2023-03-15T00:40:53.831-04:00",
          "affected_components": [
            {
              "code": "7fygdzlzf9v7",
              "name": "Editor",
              "old_status": "operational",
              "new_status": "major_outage"
            },
            {
              "code": "qmp1k3jcxdzx",
              "name": "API",
              "old_status": "operational",
              "new_status": "major_outage"
            },
            {
              "code": "mz7hvb42r41c",
              "name": "Project Hosting",
              "old_status": "operational",
              "new_status": "operational"
            },
            {
              "code": "vj4m8h9z3m0b",
              "name": "Community Site",
              "old_status": "operational",
              "new_status": "partial_outage"
            },
            {
              "code": "zvlc3gkzqxb0",
              "name": "Support Forum",
              "old_status": "operational",
              "new_status": "operational"
            }
          ],
          "deliver_notifications": false,
          "custom_tweet": null,
          "tweet_id": null
        }
      ],
      "components": [
        {
          "id": "7fygdzlzf9v7",
          "name": "Editor",
          "status": "major_outage",
          "created_at": "2016-12-12T17:24:32.054-05:00",
          "updated_at": "2023-03-15T00:40:53.765-04:00",
          "position": 1,
          "description": "glitch.com/edit/",
          "showcase": false,
          "start_date": null,
          "group_id": null,
          "page_id": "hz9lv5sckdkc",
          "group": false,
          "only_show_if_degraded": false
        },
        {
          "id": "vj4m8h9z3m0b",
          "name": "Community Site",
          "status": "partial_outage",
          "created_at": "2016-12-12T17:25:22.182-05:00",
          "updated_at": "2023-03-15T00:40:53.779-04:00",
          "position": 2,
          "description": "glitch.com",
          "showcase": false,
          "start_date": null,
          "group_id": null,
          "page_id": "hz9lv5sckdkc",
          "group": false,
          "only_show_if_degraded": false
        },
        {
          "id": "qmp1k3jcxdzx",
          "name": "API",
          "status": "major_outage",
          "created_at": "2016-12-12T17:24:38.276-05:00",
          "updated_at": "2023-03-15T00:40:53.792-04:00",
          "position": 3,
          "description": "api.glitch.com",
          "showcase": false,
          "start_date": null,
          "group_id": null,
          "page_id": "hz9lv5sckdkc",
          "group": false,
          "only_show_if_degraded": false
        },
        {
          "id": "mz7hvb42r41c",
          "name": "Project Hosting",
          "status": "operational",
          "created_at": "2016-12-12T17:24:50.880-05:00",
          "updated_at": "2023-03-06T17:44:54.751-05:00",
          "position": 4,
          "description": "your-app.glitch.me",
          "showcase": false,
          "start_date": null,
          "group_id": null,
          "page_id": "hz9lv5sckdkc",
          "group": false,
          "only_show_if_degraded": false
        },
        {
          "id": "zvlc3gkzqxb0",
          "name": "Support Forum",
          "status": "operational",
          "created_at": "2019-11-19T12:50:03.928-05:00",
          "updated_at": "2020-04-12T20:37:47.782-04:00",
          "position": 5,
          "description": "Discourse-powered forum at support.glitch.com",
          "showcase": false,
          "start_date": null,
          "group_id": null,
          "page_id": "hz9lv5sckdkc",
          "group": false,
          "only_show_if_degraded": false
        }
      ]
    }
  ],
  "scheduled_maintenances": [],
  "status": {
    "indicator": "major",
    "description": "Partial System Outage"
  }
}
