{
  "page": {
    "id": "68kf6yfjnk2d",
    "name": "Personio SE & Co. KG",
    "url": "https://status.personio.de",
    "time_zone": "Europe/Berlin",
    "updated_at": "2023-03-10T10:52:50.956+01:00"
  },
  "components": [
    {
      "id": "prkxj4m6hpm1",
      "name": "System Verfügbarkeit (System availability)",
      "status": "operational",
      "created_at": "2018-02-27T10:31:25.271+01:00",
      "updated_at": "2023-03-10T10:52:50.900+01:00",
      "position": 1,
      "description": "Informationen zur allgemeinen Systemverfügbarkeit wie Serverausfälle oder Performance Probleme. (Information about general system availability such as server outages or performance issues.)",
      "showcase": false,
      "start_date": null,
      "group_id": null,
      "page_id": "68kf6yfjnk2d",
      "group": false,
      "only_show_if_degraded": false
    },
    {
      "id": "4nndn4nksvyx",
      "name": "E-Mail Service Verfügbarkeit (Recruiting email service)",
      "status": "operational",
      "created_at": "2018-02-27T10:31:49.928+01:00",
      "updated_at": "2022-09-16T22:00:01.473+02:00",
      "position": 2,
      "description": "Informationen zu E-Mail Services wie Erinnerungen, Benachrichtigungen sowie ein- und ausgehende Bewerbernachrichten. (Information about email services such as reminders, notifications as well as in- and outbound recruiting messages.)",
      "showcase": false,
      "start_date": null,
      "group_id": null,
      "page_id": "68kf6yfjnk2d",
      "group": false,
      "only_show_if_degraded": false
    },
    {
      "id": "xbk8k300755q",
      "name": "Integrationen (Integrations)",
      "status": "operational",
      "created_at": "2018-03-08T16:18:59.737+01:00",
      "updated_at": "2023-02-02T17:35:30.921+01:00",
      "position": 3,
      "description": "Informationen zu Problemen, die uns durch Integrationspartner gemeldet werden. (Information about issues reported to us through integration partners.)",
      "showcase": false,
      "start_date": null,
      "group_id": null,
      "page_id": "68kf6yfjnk2d",
      "group": false,
      "only_show_if_degraded": false
    },
    {
      "id": "dp030hj343pg",
      "name": "Support Anwendungen (Support applications)",
      "status": "operational",
      "created_at": "2018-02-27T10:26:53.806+01:00",
      "updated_at": "2022-09-16T22:00:01.508+02:00",
      "position": 4,
      "description": "Informationen zu Anwendungen wie unserer Telefonanlage, Support E-Mails und dem Help Center. (Information about tools such as our phone system, support emails, and the help center.)",
      "showcase": false,
      "start_date": null,
      "group_id": null,
      "page_id": "68kf6yfjnk2d",
      "group": false,
      "only_show_if_degraded": false
    }
  ],
  "incidents": [
    {
      "id": "s0yhmqkxzdls",
      "name": "Global service outage",
      "status": "monitoring",
      "created_at": "2023-03-10T10:16:26.251+01:00",
      "updated_at": "2023-03-10T10:52:50.951+01:00",
      "monitoring_at": "2023-03-10T10:52:50.934+01:00",
      "resolved_at": null,
      "impact": "critical",
      "shortlink": "https://stspg.io/2q77c5sgddzz",
      "started_at": "2023-03-10T10:16:26.246+01:00",
      "page_id": "68kf6yfjnk2d",
      "incident_updates": [
        {
          "id": "835hjt5zqvz5",
          "status": "monitoring",
          "body": "A fix has been implemented and we are monitoring the results.",
          "incident_id": "s0yhmqkxzdls",
          "created_at": "2023-03-10T10:52:50.934+01:00",
          "updated_at": "2023-03-10T10:52:50.934+01:00",
          "display_at": "2023-03-10T10:52:50.934+01:00",
          "affected_components": [
            {
              "code": "prkxj4m6hpm1",
              "name": "System Verfügbarkeit (System availability)",
              "old_status": "major_outage",
              "new_status": "operational"
            }
          ],
          "deliver_notifications": false,
          "custom_tweet": null,
          "tweet_id": null
        },
        {
          "id": "k9v7rs9qmrlb",
          "status": "investigating",
          "body": "Our system is currently not available due to a global service outage. \n\nEngineers are already working to get everything up and running again.\n\nWe will keep you posted with the latest information and apologize for any inconvenience this may cause.",
          "incident_id": "s0yhmqkxzdls",
          "created_at": "2023-03-10T10:16:26.322+01:00",
          "updated_at": "2023-03-10T10:16:26.322+01:00",
          "display_at": "2023-03-10T10:16:26.322+01:00",
          "affected_components": [
            {
              "code": "prkxj4m6hpm1",
              "name": "System Verfügbarkeit (System availability)",
              "old_status": "operational",
              "new_status": "major_outage"
            }
          ],
          "deliver_notifications": false,
          "custom_tweet": null,
          "tweet_id": null
        }
      ],
      "components": [
        {
          "id": "prkxj4m6hpm1",
          "name": "System Verfügbarkeit (System availability)",
          "status": "operational",
          "created_at": "2018-02-27T10:31:25.271+01:00",
          "updated_at": "2023-03-10T10:52:50.900+01:00",
          "position": 1,
          "description": "Informationen zur allgemeinen Systemverfügbarkeit wie Serverausfälle oder Performance Probleme. (Information about general system availability such as server outages or performance issues.)",
          "showcase": false,
          "start_date": null,
          "group_id": null,
          "page_id": "68kf6yfjnk2d",
          "group": false,
          "only_show_if_degraded": false
        }
      ]
    }
  ],
  "scheduled_maintenances": [],
  "status": {
    "indicator": "none",
    "description": "All Systems Operational"
  }
}
