{
  "page": {
    "id": "mnlz85pm9zhx",
    "name": "GoDaddy",
    "url": "https://status.godaddy.com",
    "time_zone": "Etc/UTC",
    "updated_at": "2023-01-11T03:17:29.530Z"
  },
  "incidents": [
    {
      "id": "mf2wl1bv3dh5",
      "name": "GoDaddy Shopping Cart - Unable to Add Renewals and Products to the Cart",
      "status": "resolved",
      "created_at": "2023-01-11T00:02:56.309Z",
      "updated_at": "2023-01-11T03:17:29.528Z",
      "monitoring_at": null,
      "resolved_at": "2023-01-11T03:17:29.513Z",
      "impact": "critical",
      "shortlink": "https://stspg.io/ypqgd0v160yb",
      "started_at": "2023-01-11T00:02:56.292Z",
      "page_id": "mnlz85pm9zhx",
      "incident_updates": [
        {
          "id": "4r5fcswm66p6",
          "status": "resolved",
          "body": "Thank you for your patience, the issue with the GoDaddy shopping cart has been resolved.",
          "incident_id": "mf2wl1bv3dh5",
          "created_at": "2023-01-11T03:17:29.513Z",
          "updated_at": "2023-01-11T03:17:29.513Z",
          "display_at": "2023-01-11T03:17:29.513Z",
          "affected_components": [
            {
              "code": "0br8k7j1yp0j",
              "name": "GoDaddy.com - GoDaddy Shopping Cart",
              "old_status": "major_outage",
              "new_status": "operational"
            },
            {
              "code": "23f909q84rn6",
              "name": "GoDaddy.com - Order & Product Fulfillment",
              "old_status": "major_outage",
              "new_status": "operational"
            }
          ],
          "deliver_notifications": false,
          "custom_tweet": null,
          "tweet_id": null
        },
        {
          "id": "17g9lc298bs2",
          "status": "investigating",
          "body": "We are currently investigating an issue being unable to add renewals and products to the GoDaddy Shopping Cart. Issues also include being unable to cancel renewals or update payment methods.",
          "incident_id": "mf2wl1bv3dh5",
          "created_at": "2023-01-11T00:02:56.445Z",
          "updated_at": "2023-01-11T00:02:56.445Z",
          "display_at": "2023-01-11T00:02:56.445Z",
          "affected_components": [
            {
              "code": "0br8k7j1yp0j",
              "name": "GoDaddy.com - GoDaddy Shopping Cart",
              "old_status": "operational",
              "new_status": "major_outage"
            },
            {
              "code": "23f909q84rn6",
              "name": "GoDaddy.com - Order & Product Fulfillment",
              "old_status": "operational",
              "new_status": "major_outage"
            }
          ],
          "deliver_notifications": false,
          "custom_tweet": null,
          "tweet_id": null
        }
      ],
      "components": [
        {
          "id": "0br8k7j1yp0j",
          "name": "GoDaddy Shopping Cart",
          "status": "operational",
          "created_at": "2022-07-21T15:21:00.021Z",
          "updated_at": "2023-01-11T03:17:29.468Z",
          "position": 2,
          "description": null,
          "showcase": false,
          "start_date": "2022-07-21",
          "group_id": "90nm5dkqh1mn",
          "page_id": "mnlz85pm9zhx",
          "group": false,
          "only_show_if_degraded": false
        },
        {
          "id": "23f909q84rn6",
          "name": "Order & Product Fulfillment",
          "status": "operational",
          "created_at": "2022-07-21T15:23:01.875Z",
          "updated_at": "2023-01-11T03:17:29.484Z",
          "position": 7,
          "description": null,
          "showcase": false,
          "start_date": "2022-07-21",
          "group_id": "90nm5dkqh1mn",
          "page_id": "mnlz85pm9zhx",
          "group": false,
          "only_show_if_degraded": false
        }
      ]
    },
    {
      "id": "3791zpl0d8fl",
      "name": "WordPress Hosting and Website Builder Outage",
      "status": "resolved",
      "created_at": "2023-01-06T21:37:06.954Z",
      "updated_at": "2023-01-06T21:55:22.751Z",
      "monitoring_at": null,
      "resolved_at": "2023-01-06T21:55:22.737Z",
      "impact": "major",
      "shortlink": "https://stspg.io/xt6ksr0646q7",
      "started_at": "2023-01-06T21:37:06.944Z",
      "page_id": "mnlz85pm9zhx",
      "incident_updates": [
        {
          "id": "fz9pfv4whlx4",
          "status": "resolved",
          "body": "Thank you for your patience, this issue has been resolved.",
          "incident_id": "3791zpl0d8fl",
          "created_at": "2023-01-06T21:55:22.737Z",
          "updated_at": "2023-01-06T21:55:22.737Z",
          "display_at": "2023-01-06T21:55:22.737Z",
          "affected_components": [
            {
              "code": "fmkx7hc1h5p7",
              "name": "WordPress Hosting - WordPress Hosting",
              "old_status": "major_outage",
              "new_status": "operational"
            },
            {
              "code": "7d53sp8fbhv1",
              "name": "Websites and Stores - Website Builder",
              "old_status": "partial_outage",
              "new_status": "operational"
            }
          ],
          "deliver_notifications": false,
          "custom_tweet": null,
          "tweet_id": null
        },
        {
          "id": "0vl3g4lq34k5",
          "status": "investigating",
          "body": "We are currently investigating a connectivity issue impacting WordPress Hosting and Website Builder in the European region.",
          "incident_id": "3791zpl0d8fl",
          "created_at": "2023-01-06T21:37:07.036Z",
          "updated_at": "2023-01-06T21:37:07.036Z",
          "display_at": "2023-01-06T21:37:07.036Z",
          "affected_components": [
            {
              "code": "fmkx7hc1h5p7",
              "name": "WordPress Hosting - WordPress Hosting",
              "old_status": "operational",
              "new_status": "major_outage"
            },
            {
              "code": "7d53sp8fbhv1",
              "name": "Websites and Stores - Website Builder",
              "old_status": "operational",
              "new_status": "partial_outage"
            }
          ],
          "deliver_notifications": false,
          "custom_tweet": null,
          "tweet_id": null
        }
      ],
      "components": [
        {
          "id": "fmkx7hc1h5p7",
          "name": "WordPress Hosting",
          "status": "operational",
          "created_at": "2022-07-21T15:16:16.001Z",
          "updated_at": "2023-01-06T21:55:22.705Z",
          "position": 1,
          "description": null,
          "showcase": false,
          "start_date": "2022-07-21",
          "group_id": "pxr5zqtws0jx",
          "page_id": "mnlz85pm9zhx",
          "group": false,
          "only_show_if_degraded": false
        },
        {
          "id": "7d53sp8fbhv1",
          "name": "Website Builder",
          "status": "operational",
          "created_at": "2022-07-21T15:31:46.184Z",
          "updated_at": "2023-01-06T21:55:22.690Z",
          "position": 1,
          "description": "This may also include: Online Appointments.",
          "showcase": false,
          "start_date": "2022-07-21",
          "group_id": "js6vw7f9crfq",
          "page_id": "mnlz85pm9zhx",
          "group": false,
          "only_show_if_degraded": false
        }
      ]
    },
    {
      "id": "w3td6dklscpq",
      "name": "GoDaddy Messaging Support Services Degraded",
      "status": "resolved",
      "created_at": "2023-01-06T08:37:20.820Z",
      "updated_at": "2023-01-06T11:42:26.018Z",
      "monitoring_at": null,
      "resolved_at": "2023-01-06T11:42:26.003Z",
      "impact": "minor",
      "shortlink": "https://stspg.io/wzzbbb7qytxy",
      "started_at": "2023-01-06T08:37:20.813Z",
      "page_id": "mnlz85pm9zhx",
      "incident_updates": [
        {
          "id": "dz2ychsv0c4w",
          "status": "resolved",
          "body": "The issue has been resolved.",
          "incident_id": "w3td6dklscpq",
          "created_at": "2023-01-06T11:42:26.003Z",
          "updated_at": "2023-01-06T11:42:26.003Z",
          "display_at": "2023-01-06T11:42:26.003Z",
          "affected_components": [
            {
              "code": "bjf0bghd2f5p",
              "name": "GoDaddy Support - Messaging Support Services",
              "old_status": "degraded_performance",
              "new_status": "operational"
            }
          ],
          "deliver_notifications": false,
          "custom_tweet": null,
          "tweet_id": null
        },
        {
          "id": "cwl961x2xvfp",
          "status": "investigating",
          "body": "We are currently investigating an issue impacting GoDaddy Messaging Support to be degraded globally.",
          "incident_id": "w3td6dklscpq",
          "created_at": "2023-01-06T08:37:20.893Z",
          "updated_at": "2023-01-06T08:37:20.893Z",
          "display_at": "2023-01-06T08:37:20.893Z",
          "affected_components": [
            {
              "code": "bjf0bghd2f5p",
              "name": "GoDaddy Support - Messaging Support Services",
              "old_status": "operational",
              "new_status": "degraded_performance"
            }
          ],
          "deliver_notifications": false,
          "custom_tweet": null,
          "tweet_id": null
        }
      ],
      "components": [
        {
          "id": "bjf0bghd2f5p",
          "name": "Messaging Support Services",
          "status": "operational",
          "created_at": "2022-07-21T15:22:27.858Z",
          "updated_at": "2023-01-06T11:42:25.969Z",
          "position": 1,
          "description": null,
          "showcase": false,
          "start_date": "2022-07-21",
          "group_id": "qg95bvc5b09k",
          "page_id": "mnlz85pm9zhx",
          "group": false,
          "only_show_if_degraded": false
        }
      ]
    },
    {
      "id": "jzqxshpl7dck",
      "name": "GoDaddy Support Services Degraded",
      "status": "resolved",
      "created_at": "2023-01-05T19:30:42.000Z",
      "updated_at": "2023-01-05T22:13:17.828Z",
      "monitoring_at": null,
      "resolved_at": "2023-01-05T22:13:17.813Z",
      "impact": "major",
      "shortlink": "https://stspg.io/pvwl3jp5q0l4",
      "started_at": "2023-01-05T19:30:42.000Z",
      "page_id": "mnlz85pm9zhx",
      "incident_updates": [
        {
          "id": "y4dkgxmcg6xs",
          "status": "resolved",
          "body": "Thank you for your patience, this issue has been resolved.",
          "incident_id": "jzqxshpl7dck",
          "created_at": "2023-01-05T22:13:17.813Z",
          "updated_at": "2023-01-05T22:13:17.813Z",
          "display_at": "2023-01-05T22:13:17.813Z",
          "affected_components": [
            {
              "code": "bjf0bghd2f5p",
              "name": "GoDaddy Support - Messaging Support Services",
              "old_status": "partial_outage",
              "new_status": "operational"
            },
            {
              "code": "h0mzct458h96",
              "name": "GoDaddy Support - Voice Support Services",
              "old_status": "partial_outage",
              "new_status": "operational"
            }
          ],
          "deliver_notifications": false,
          "custom_tweet": null,
          "tweet_id": null
        },
        {
          "id": "rpygpf5b9jm3",
          "status": "investigating",
          "body": "We are currently investigating an issue impacting GoDaddy Support from North America.",
          "incident_id": "jzqxshpl7dck",
          "created_at": "2023-01-05T21:51:42.334Z",
          "updated_at": "2023-01-05T21:52:29.893Z",
          "display_at": "2023-01-05T19:30:42.000Z",
          "affected_components": [
            {
              "code": "bjf0bghd2f5p",
              "name": "GoDaddy Support - Messaging Support Services",
              "old_status": "operational",
              "new_status": "partial_outage"
            },
            {
              "code": "h0mzct458h96",
              "name": "GoDaddy Support - Voice Support Services",
              "old_status": "operational",
              "new_status": "partial_outage"
            }
          ],
          "deliver_notifications": false,
          "custom_tweet": null,
          "tweet_id": null
        }
      ],
      "components": [
        {
          "id": "bjf0bghd2f5p",
          "name": "Messaging Support Services",
          "status": "operational",
          "created_at": "2022-07-21T15:22:27.858Z",
          "updated_at": "2023-01-06T11:42:25.969Z",
          "position": 1,
          "description": null,
          "showcase": false,
          "start_date": "2022-07-21",
          "group_id": "qg95bvc5b09k",
          "page_id": "mnlz85pm9zhx",
          "group": false,
          "only_show_if_degraded": false
        },
        {
          "id": "h0mzct458h96",
          "name": "Voice Support Services",
          "status": "operational",
          "created_at": "2022-07-25T22:27:18.302Z",
          "updated_at": "2023-01-05T22:13:17.782Z",
          "position": 2,
          "description": null,
          "showcase": false,
          "start_date": "2022-07-25",
          "group_id": "qg95bvc5b09k",
          "page_id": "mnlz85pm9zhx",
          "group": false,
          "only_show_if_degraded": false
        }
      ]
    },
    {
      "id": "pwtqzwq7ct49",
      "name": "GoDaddy Shopping Cart Outage",
      "status": "resolved",
      "created_at": "2023-01-05T15:59:47.000Z",
      "updated_at": "2023-01-05T16:41:44.492Z",
      "monitoring_at": null,
      "resolved_at": "2023-01-05T16:15:55.000Z",
      "impact": "critical",
      "shortlink": "https://stspg.io/nv1tsl02ttht",
      "started_at": "2023-01-05T15:59:47.000Z",
      "page_id": "mnlz85pm9zhx",
      "incident_updates": [
        {
          "id": "xq67b45twt6l",
          "status": "resolved",
          "body": "This incident has been resolved.",
          "incident_id": "pwtqzwq7ct49",
          "created_at": "2023-01-05T16:40:55.633Z",
          "updated_at": "2023-01-05T16:41:44.477Z",
          "display_at": "2023-01-05T16:15:55.000Z",
          "affected_components": [
            {
              "code": "0br8k7j1yp0j",
              "name": "GoDaddy.com - GoDaddy Shopping Cart",
              "old_status": "major_outage",
              "new_status": "operational"
            }
          ],
          "deliver_notifications": false,
          "custom_tweet": null,
          "tweet_id": null
        },
        {
          "id": "vb6gpf1085r1",
          "status": "investigating",
          "body": "We are currently investigating an outage with the GoDaddy Shopping Cart.",
          "incident_id": "pwtqzwq7ct49",
          "created_at": "2023-01-05T16:40:47.908Z",
          "updated_at": "2023-01-05T16:41:43.075Z",
          "display_at": "2023-01-05T15:59:47.000Z",
          "affected_components": [
            {
              "code": "0br8k7j1yp0j",
              "name": "GoDaddy.com - GoDaddy Shopping Cart",
              "old_status": "operational",
              "new_status": "major_outage"
            }
          ],
          "deliver_notifications": false,
          "custom_tweet": null,
          "tweet_id": null
        }
      ],
      "components": [
        {
          "id": "0br8k7j1yp0j",
          "name": "GoDaddy Shopping Cart",
          "status": "operational",
          "created_at": "2022-07-21T15:21:00.021Z",
          "updated_at": "2023-01-11T03:17:29.468Z",
          "position": 2,
          "description": null,
          "showcase": false,
          "start_date": "2022-07-21",
          "group_id": "90nm5dkqh1mn",
          "page_id": "mnlz85pm9zhx",
          "group": false,
          "only_show_if_degraded": false
        }
      ]
    }
  ]
}
